{
    "backend": "flask",
    "db_name": "",
    "db_pass": "",
    "db_type": "",
    "db_user": "",
    "dbms": "0",
    "description": "generated product",
    "design": "datta-able",
    "docker": "1",
    "err_code": 0,
    "frontend": "",
    "github_repo": "https://github.com/appseed-projects/0ae42450-b9ce-4515-ba61-45db8357e706",
    "heroku": "0",
    "pattern": "mvc",
    "pro": "0",
    "task_id": "0ae42450-b9ce-4515-ba61-45db8357e706",
    "task_info": "Upload Sources [0%] - 132 files",
    "task_output": "0ae42450-b9ce-4515-ba61-45db8357e706.zip",
    "task_result": "SUCCESS",
    "task_state": "RUNNING",
    "task_ts_end": "2022-06-10-18-22-05",
    "task_ts_start": "2022-06-10-18-22-03"
}